{
  "title": "Dashboard",
  "loading": "Loading...",
  "greeting": {
    "morning": "good morning",
    "afternoon": "Good day",
    "evening": "Good Evening"
  },
  "refresh": "Refresh",
  "refreshing": "It's being renewed...",
  "refreshed": "Data updated",
  "refreshError": "Update failed",
  "user": "User",
  "noSalesData": "No sales data yet",
  "noActivities": "No activity yet",
  "selectFormat": "Select Format",
  "reportPreparing": "The report is being prepared...",
  "reportDownloaded": "The report has been downloaded.",
  "reportError": "The report could not be received.",
  "stats": {
    "totalRevenue": "Total Turnover",
    "activeOpportunities": "Active Opportunities",
    "newLeads": "New Candidates",
    "pendingOrders": "Pending Orders"
  },
  "salesAnalysis": "Sales Analysis",
  "targetVsActual": "Goal vs Achieved",
  "latestActivities": "Latest Activities",
  "viewAll": "See All",
  "reportDownload": "Download Report",
  "quickAction": "Fast Transaction",
  "activityType": {
    "meeting": "meeting",
    "call": "Search",
    "email": "Email",
    "general": "General"
  },
  "noDate": "no date",
  "unnamedActivity": "Anonymous Activity",
  "monthsShort": {
    "jan": "January",
    "feb": "feb",
    "mar": "Mar",
    "apr": "Apr",
    "may": "May",
    "jun": "pleasure",
    "jul": "Jul",
    "aug": "Aug",
    "sep": "Sep",
    "oct": "Oct",
    "nov": "muscle",
    "dec": "Search"
  },
  "quickStats": {
    "pendingTasks": "Pending Tasks",
    "checkTasks": "Check the task list",
    "openQuotations": "Open Offers",
    "reviewQuotations": "Check out the offers",
    "criticalStock": "Critical Stock",
    "stockStatus": "See stock status"
  },
  "sidebar": {
    "customers": "Customers",
    "customerManagement": "Customer Management",
    "salesManagement": "Sales Funnel",
    "demandCreateWizard": "Create New Request",
    "quotationCreateWizard": "Create New Offer",
    "orderCreateWizard": "Create New Order",
    "activities": "Planning",
    "activityManagement": "Activity Management"
  },
  "errors": {
    "listLoadFailed": "Failed to retrieve list",
    "pathListLoadFailed": "Could not get route list",
    "projectNotFound": "Project not found"
  },
  "aquaDashboard": {
    "title": "Aqua Dashboard",
    "description": "General production and project status of your facility.",
    "selectedProject": "Displayed Project",
    "selectProjectPlaceholder": "Choose from all projects...",
    "facilitySummary": "Facility Overview",
    "projectDetail": "Project Detail",
    "dataLoadFailed": "Data could not be retrieved.",
    "detailReportButton": "Detail Report",
    "selectProjectHint": "Please select a project above to see its details.",
    "dailyFlow": "Daily Data Stream",
    "dailyFlowEmptyTitle": "There is no daily activity recorded for this cage yet.",
    "dailyFlowEmptyDescription": "Once feeding, mortality, transfer, shipment, weather, net or other daily operations are entered, they will appear here day by day.",
    "activeProjectFilters": {
      "title": "Active Project Filters",
      "description": "The projects you select filter the cards and lists below.",
      "cageSortLockedHint": "Project filters are locked while cage sort mode is on."
    },
    "yesterdayAlert": {
      "title": "Yesterday's entries are missing",
      "description": "No journal entries found for date {{date}}. Control feeding, weather, net, transfer and other daily operations."
    },
    "projectSelector": {
      "title": "Project Selection",
      "description": "Filter the dashboard view by selecting one or more projects.",
      "searchPlaceholder": "Search for project code or name...",
      "selectedCount": "Selected: {{count}}",
      "emptySelection": "No project selected yet",
      "activeBadge": "active",
      "noResults": "No project matching your search was found.",
      "loadingApply": "Loading projects...",
      "apply": "Apply",
      "openButton": "Select Project",
      "closeButton": "Close",
      "clearButton": "clear",
      "applyButton": "Apply",
      "cancelButton": "Cancel",
      "resetButton": "reset"
    },
    "stats": {
      "activeCages": "Active Cage",
      "liveFish": "Live Fish",
      "cageFishStock": "Cage Stock",
      "warehouseFishStock": "Warehouse Stock",
      "totalSystemFishStock": "Total System Stock",
      "cageBiomass": "Cage Biomass",
      "warehouseBiomass": "Warehouse Biomass",
      "totalBiomass": "Total Biomass",
      "totalFeed": "Total Feed"
    },
    "detailTypes": {
      "feeding": "Feeding Detail",
      "netOperation": "Network Operation",
      "transfer": "Transfer",
      "stockConvert": "Stock Conversion",
      "shipment": "Shipment"
    },
    "detailDialog": {
      "date": "Date: {{date}}"
    },
    "dailyTable": {
      "date": "date",
      "feedGram": "Feed (g)",
      "stock": "stock",
      "dead": "Wastage",
      "delta": "delta",
      "biomassDelta": "Bio Delta",
      "weather": "weather",
      "net": "network",
      "netOperation": "Network Processing",
      "transfer": "Transfer",
      "shipment": "Shipment",
      "shipmentOperation": "Shipping Process",
      "status": "Status",
      "stockCount": "{{count}} stock",
      "operationCount": "{{count}} transaction",
      "netOperationCount": "{{count}} network processing",
      "shipmentCount": "{{count}} shipping transaction",
      "stockConvertCount": "{{count}} conversion process",
      "transferQty": "{{count}} quantity",
      "fed": "fed",
      "notFed": "not fed",
      "criticalDay": "Critical Day"
    },
    "dailyCards": {
      "feed": "bait",
      "dead": "Wastage",
      "delta": "delta",
      "biomass": "biomass"
    },
    "dailySections": {
      "feedStocks": "Feed Stocks",
      "net": "network",
      "netOperation": "Network Processing",
      "transfer": "Transfer",
      "transferQty": "Number of Transfers",
      "shipment": "Shipment",
      "shipmentOperation": "Shipping Process"
    },
    "projectDialog": {
      "fish": "Fish",
      "dead": "Mortality",
      "feedGram": "Feed",
      "cages": "Cages",
      "cagePools": "Cage Pools",
      "clickForDailyDetail": "Click for daily details",
      "subtitle": "Project summary & cage data"
    },
    "projectSummary": {
      "totalDeadCount": "Mortality Qty",
      "totalDeadKg": "Mortality Kg",
      "totalShipmentCount": "Sales Qty",
      "totalShipmentKg": "Sales Kg",
      "measurementGram": "Avg Weight",
      "fcr": "FCR",
      "activeCage": "cages",
      "cageFish": "cage fish",
      "warehouseFish": "warehouse",
      "totalFish": "total fish"
    },
    "cageCard": {
      "totalDeadCount": "Mortality Qty",
      "shipmentCount": "Sales Qty",
      "stockCount": "Stock Qty",
      "totalDeadKg": "Mortality Kg",
      "shipmentKg": "Sales Kg",
      "stockKg": "Stock Kg",
      "measurementGram": "Measured Gram",
      "feedKg": "Fed Feed Kg",
      "fcr": "FCR",
      "survivalRate": "Survival Rate",
      "quickDailyEntry": "Daily Login",
      "expandFullscreen": "Expand to fullscreen",
      "closeHint": "to close"
    },
    "controls": {
      "viewAndProject": "Appearance and Project",
      "projectCountAndView": "{{count}} Project • {{view}}",
      "cardView": "card",
      "listView": "List",
      "viewType": "Appearance",
      "projectSelection": "Project Selection",
      "selectAll": "Select All",
      "clear": "clear",
      "close": "Close",
      "detail": "Detail",
      "cageSortToggle": "Cage order",
      "cageSortToggleHint": "Turns on cage sort, selects all projects, and lists cages by code. Press again to turn off and clear the project selection.",
      "cageSortFilterLockedHint": "Project filters cannot be changed while cage sort mode is on."
    },
    "cageSortSection": {
      "title": "Sorted by cage code",
      "description": "{{projectCount}} projects, {{cageCount}} cages total; order is by cage code (then project code if tied)."
    },
    "selectedProjects": "Selected Projects",
    "listTable": {
      "cage": "cage",
      "project": "Project",
      "fish": "Pisces",
      "dead": "Wastage",
      "shipment": "Sales",
      "stockKg": "Stock Kg",
      "measurementGram": "Measured Gram",
      "feedKg": "Feed Kg",
      "fcr": "FCR",
      "survivalRate": "Survival Rate",
      "action": "transaction",
      "dailyFlowButton": "Daily Stream"
    }
  }
}
