{
  "title": "Aktivite Yönetimi",
  "description": "Aktiviteleri yönetin ve düzenleyin",
  "create": "Yeni Aktivite",
  "createDescription": "Yeni aktivite bilgilerini girin",
  "edit": "Aktivite Düzenle",
  "editButton": "Düzenle",
  "editDescription": "Aktivite bilgilerini düzenleyin",
  "delete": "Sil",
  "deleteTitle": "Aktiviteyi Sil",
  "subject": "Konu",
  "activityType": "Aktivite Tipi",
  "potentialCustomerId": "Potansiyel Müşteri",
  "potentialCustomer": "Müşteri",
  "customer": "Müşteri",
  "selectCustomer": "Müşteri Seç",
  "erpCustomerCode": "ERP Müşteri Kodu",
  "product": "Stok/Ürün",
  "selectProduct": "Stok/Ürün Seç",
  "status": "Durum",
  "isCompleted": "Tamamlandı",
  "priority": "Öncelik",
  "contactId": "İletişim",
  "contact": "Kişi",
  "assignedUserId": "Atanan Kullanıcı",
  "assignedUser": "Sorumlu",
  "activityDate": "Aktivite Tarihi",
  "activityDateRequired": "Aktivite tarihi gereklidir",
  "createdDate": "Oluşturulma Tarihi",
  "updatedDate": "Güncellenme Tarihi",
  "actions": "İşlemler",
  "search": "Ara",
  "filterByActivityType": "Aktivite Tipine Göre Filtrele",
  "filterByStatus": "Duruma Göre Filtrele",
  "filterByPriority": "Önceliğe Göre Filtrele",
  "filterByPotentialCustomer": "Müşteriye Göre Filtrele",
  "filterByContact": "Kişiye Göre Filtrele",
  "filterByAssignedUser": "Atanan Kullanıcıya Göre Filtrele",
  "filterByIsCompleted": "Tamamlanma Durumuna Göre Filtrele",
  "filterByCreatedDateRange": "Oluşturulma Tarihi Aralığına Göre Filtrele",
  "noData": "Veri bulunamadı",
  "confirmDelete": "Bu aktiviteyi silmek istediğinizden emin misiniz?",
  "createSuccess": "Aktivite başarıyla oluşturuldu",
  "updateSuccess": "Aktivite başarıyla güncellendi",
  "deleteSuccess": "Aktivite başarıyla silindi",
  "createError": "Aktivite oluşturulurken bir hata oluştu",
  "updateError": "Aktivite güncellenirken bir hata oluştu",
  "deleteError": "Aktivite silinirken bir hata oluştu",
  "subjectRequired": "Konu gereklidir",
  "subjectMaxLength": "Konu en fazla 100 karakter olabilir",
  "descriptionMaxLength": "Açıklama en fazla 500 karakter olabilir",
  "activityTypeRequired": "Aktivite tipi seçimi gereklidir",
  "activityTypeMaxLength": "Aktivite tipi en fazla 50 karakter olabilir",
  "statusRequired": "Durum seçimi gereklidir",
  "statusMaxLength": "Durum en fazla 50 karakter olabilir",
  "priorityMaxLength": "Öncelik en fazla 50 karakter olabilir",
  "enterSubject": "Konu Girin",
  "enterDescription": "Açıklama Girin (Opsiyonel)",
  "selectActivityType": "Aktivite Tipi Seçin",
  "selectPotentialCustomer": "Potansiyel Müşteri Seçin (Opsiyonel)",
  "enterErpCustomerCode": "ERP Müşteri Kodu Girin (Opsiyonel)",
  "selectStatus": "Durum Seçin",
  "selectPriority": "Öncelik Seçin (Opsiyonel)",
  "selectContact": "İletişim Seçin (Opsiyonel)",
  "selectAssignedUser": "Atanan Kullanıcı Seçin (Opsiyonel)",
  "noCustomerSelected": "Müşteri seçilmedi",
  "noContactSelected": "İletişim seçilmedi",
  "noUserSelected": "Kullanıcı seçilmedi",
  "noPrioritySelected": "Öncelik seçilmedi",
  "selectCustomerFirst": "Önce müşteri seçin",
  "loading": "Yükleniyor...",
  "save": "Kaydet",
  "saving": "Kaydediliyor...",
  "cancel": "İptal",
  "previous": "Önceki",
  "next": "Sonraki",
  "productDisplay": "{{code}} - {{name}}",
  "erpLabel": "ERP: {{code}}",
  "close": "Kapat",
  "clearFilters": "Filtreleri Temizle",
  "applyFilters": "Filtreleri Uygula",
  "advancedFilter": {
    "title": "Gelişmiş Filtre",
    "add": "Filtre Ekle",
    "column": "Sütun",
    "operator": "Operatör",
    "value": "Değer",
    "search": "Ara",
    "clear": "Temizle",
    "remove": "Kaldır",
    "equals": "Eşittir",
    "contains": "İçerir",
    "startsWith": "Şununla başlar",
    "endsWith": "Şununla biter",
    "operatorEquals": "Eşittir",
    "operatorContains": "İçerir",
    "operatorStartsWith": "Şununla başlar",
    "operatorEndsWith": "Şununla biter",
    "operator>": ">",
    "operator>=": ">=",
    "operator<": "<",
    "operator<=": "<=",
    "true": "Evet",
    "false": "Hayır",
    "columnSubject": "Konu",
    "columnDescription": "Açıklama",
    "columnCustomerId": "Müşteri No",
    "columnActivityTypeId": "Aktivite Tipi No",
    "columnPriority": "Öncelik",
    "columnDueDate": "Bitiş Tarihi",
    "columnIsCompleted": "Tamamlandı",
    "filterButton": "Gelişmiş Filtre"
  },
  "columnCustomization": {
    "hiddenColumns": "Gizlenen Sütunlar",
    "visibleColumns": "Gösterilecek Sütunlar",
    "moveUp": "Yukarı",
    "moveDown": "Aşağı"
  },
  "markAsCompleted": "Tamamla",
  "markAsInProgress": "Devam Et",
  "cancelActivity": "İptal",
  "confirmMarkAsCompleted": "Bu aktiviteyi tamamlandı olarak işaretlemek istediğinizden emin misiniz?",
  "confirmMarkAsInProgress": "Bu aktiviteyi devam ediyor olarak işaretlemek istediğinizden emin misiniz?",
  "confirmCancel": "Bu aktiviteyi iptal etmek istediğinizden emin misiniz?",
  "markAsCompletedSuccess": "Aktivite tamamlandı olarak işaretlendi",
  "markAsInProgressSuccess": "Aktivite devam ediyor olarak işaretlendi",
  "cancelSuccess": "Aktivite iptal edildi",
  "statusChangeWarning": "Durumu değiştirmek istediğinizden emin misiniz?",
  "autoCompleteStatus": "Durum 'Tamamlandı' olarak ayarlandığında otomatik olarak işaretlenecek",
  "activityTypeCall": "Arama",
  "activityTypeMeeting": "Toplantı",
  "activityTypeEmail": "E-posta",
  "activityTypeTask": "Görev",
  "activityTypeNote": "Not",
  "activityTypeEvent": "Etkinlik",
  "statusScheduled": "Planlandı",
  "statusInProgress": "Devam Ediyor",
  "statusCompleted": "Tamamlandı",
  "statusCanceled": "İptal Edildi",
  "statusPostponed": "Ertelendi",
  "priorityLow": "Düşük",
  "priorityMedium": "Orta",
  "priorityHigh": "Yüksek",
  "allActivityTypes": "Tüm Aktivite Tipleri",
  "allStatuses": "Tüm Durumlar",
  "allPriorities": "Tüm Öncelikler",
  "completedActivities": "Tamamlanan Aktiviteler",
  "pendingActivities": "Bekleyen Aktiviteler",
  "highPriorityActivities": "Yüksek Öncelikli Aktiviteler",
  "noCompletedActivities": "Tamamlanan aktivite bulunamadı",
  "noPendingActivities": "Bekleyen aktivite bulunamadı",
  "activityDetails": "Aktivite Detayları",
  "customerInformation": "Müşteri Bilgileri",
  "contactInformation": "İletişim Bilgileri",
  "assignedUserInformation": "Atanan Kullanıcı Bilgileri",
  "calendarView": "Takvim Görünümü",
  "kanbanView": "Kanban Görünümü",
  "tableView": "Tablo Görünümü",
  "switchToCalendar": "Takvim Görünümüne Geç",
  "switchToKanban": "Kanban Görünümüne Geç",
  "switchToTable": "Tablo Görünümüne Geç",
  "table": {
    "id": "ID",
    "subject": "Konu",
    "activityType": "Aktivite Tipi",
    "status": "Durum",
    "priority": "Öncelik",
    "potentialCustomer": "Müşteri",
    "contact": "Kişi",
    "assignedUser": "Sorumlu",
    "isCompleted": "Tamamlandı",
    "createdDate": "Oluşturulma Tarihi",
    "updatedDate": "Güncellenme Tarihi",
    "showing": "{{from}}-{{to}} / {{total}} gösteriliyor",
    "page": "Sayfa {{current}} / {{total}}"
  },
  "common": {
    "sidebar": {
      "netsisMirror": "Netsis Mirror",
      "netsisMirrorCustomers": "Netsis Cariler",
      "netsisMirrorStocks": "Netsis Stoklar",
      "netsisMirrorWarehouses": "Netsis Depoları",
      "netsisMirrorBranches": "Netsis Şubeler",
      "aquaCageWarehouseMappings": "Kafes Depo Eşlemeleri",
      "aquaOpeningImport": "Açılış Girişi",
      "aquaWarehouseTransfers": "Depo Transferleri",
      "aquaCageWarehouseTransfers": "Kafes-Depo Transferleri",
      "aquaWarehouseCageTransfers": "Depo-Kafes Transferleri",
      "aquaWarehouseTransferLines": "Depo Transfer Satırları",
      "aquaCageWarehouseTransferLines": "Kafes-Depo Transfer Satırları",
      "aquaWarehouseCageTransferLines": "Depo-Kafes Transfer Satırları"
    }
  },
  "dashboard": {
    "aquaDashboard": {
      "dailyFlowEmptyTitle": "Günlük akışta veri bulunamadı",
      "dailyFlowEmptyDescription": "Bu tarihte veya bu filtrelerle gösterilecek bir kayıt bulunmuyor.",
      "activeProjectFilters": {
        "cageSortLockedHint": "Kafes sıralaması kilitli ise otomatik sıralama uygulanamaz."
      },
      "projectSelector": {
        "loadingApply": "Uygulanıyor..."
      },
      "stats": {
        "cageFishStock": "Kafes Balık Stoğu",
        "warehouseFishStock": "Depo Balık Stoğu",
        "totalSystemFishStock": "Toplam Sistem Balık Stoğu",
        "cageBiomass": "Kafes Biyokütle",
        "warehouseBiomass": "Depo Biyokütle"
      },
      "projectDialog": {
        "subtitle": "Proje özeti ve akış detayını bu ekrandan görün."
      },
      "projectSummary": {
        "totalDeadCount": "Toplam Ölü Sayısı",
        "totalDeadKg": "Toplam Ölü Kg",
        "totalShipmentCount": "Toplam Sevkiyat Sayısı",
        "totalShipmentKg": "Toplam Sevkiyat Kg",
        "measurementGram": "Ölçüm (g)",
        "fcr": "FCR",
        "activeCage": "Aktif Kafes",
        "cageFish": "Kafes Balık Stoğu",
        "warehouseFish": "Depo Balık Stoğu",
        "totalFish": "Toplam Balık"
      },
      "cageCard": {
        "totalDeadCount": "Toplam Ölü Sayısı",
        "shipmentCount": "Sevkiyat Sayısı",
        "stockCount": "Stok Sayısı",
        "totalDeadKg": "Toplam Ölü Kg",
        "shipmentKg": "Toplam Sevkiyat Kg",
        "stockKg": "Toplam Stok Kg",
        "measurementGram": "Ölçüm (g)",
        "feedKg": "Yem Kg",
        "fcr": "FCR"
      },
      "controls": {
        "detail": "Detay",
        "cageSortFilterLockedHint": "Kafes sıralama filtresi kilitliyse sıralama değiştirilemez."
      },
      "listTable": {
        "shipment": "Sevkiyat",
        "stockKg": "Stok Kg",
        "measurementGram": "Ölçüm (g)",
        "feedKg": "Yem Kg",
        "fcr": "FCR"
      }
    }
  }
}
